__init__.py
tg_delivery_client/__init__.py
tg_delivery_client/amqp_publisher.py
tg_delivery_client/domain.py
tg_delivery_client/facade.py
tg_delivery_client/options.py
tg_delivery_client/ports.py
tg_delivery_client/retry.py
tg_delivery_client/serializers.py
tg_delivery_client-0.1.0.dist-info/METADATA
tg_delivery_client-0.1.0.dist-info/WHEEL
tg_delivery_client-0.1.0.dist-info/top_level.txt
tg_delivery_client-0.1.0.dist-info/RECORD
