Metadata-Version: 2.4
Name: tg-delivery-client
Version: 0.1.0
Summary: AMQP publisher and a facade for sending commands to the Telegram delivery service.
Author: k3l3vr444
License: MIT
Requires-Python: >=3.12
Requires-Dist: aiormq>=6.8.0
Requires-Dist: pamqp>=3.3.0
